setup.py
bbiz_pv/__init__.py
bbiz_pv/one.py
bbiz_pv/two.py
bbiz_pv.egg-info/PKG-INFO
bbiz_pv.egg-info/SOURCES.txt
bbiz_pv.egg-info/dependency_links.txt
bbiz_pv.egg-info/top_level.txt