Metadata-Version: 2.1
Name: bbiz_pv
Version: 0.0.1
Summary: My Package
Author: Paulin
Author-email: po11ypotapova@yandex.ru
